ALU_Register/alu_register.v
`timescale 1ns / 1ps

module alu_register #(
    parameter WIDTH = 8
)(
    input  wire             clk_i,
    input  wire             rst_i,
    input  wire             valid_i,
    input  wire [WIDTH-1:0] first_i,
    input  wire [WIDTH-1:0] second_i,
    input  wire [1:0]       opcode_i,

    output reg              valid_o,
    output reg  [WIDTH-1:0] result_o
);

    reg [WIDTH-1:0] alu_result;

    always @(*) begin
        alu_result = {WIDTH{1'b0}}; 
        
        case (opcode_i)
            2'b00:   alu_result = $signed(first_i) + $signed(second_i); // Сложение (знаковое)
            2'b01:   alu_result = (second_i <= first_i);                // second_i <= first_i
            2'b10:   alu_result = second_i << first_i;                  // Логический сдвиг second_i влево на first_i
            2'b11:   alu_result = ~(first_i | second_i);                // Побитовое НЕ-ИЛИ
            
            default: alu_result = {WIDTH{1'b0}};
        endcase
    end

    always @(posedge clk_i)
    begin
        if (rst_i) begin
            valid_o <= 1'b0;
        end
        else begin
            valid_o <= valid_i;
        end

        if (valid_i) begin
            result_o <= alu_result;
        end
    end

endmodule

task2_verilog/alu_register_tb.v
`timescale 1ns / 1ps

module alu_register_tb();

    localparam WIDTH = 8;

    reg             clk_i;
    reg             rst_i;
    reg             valid_i;
    reg [WIDTH-1:0] first_i;
    reg [WIDTH-1:0] second_i;
    reg [1:0]       opcode_i;

    wire             valid_o;
    wire [WIDTH-1:0] result_o;

    alu_register #(
        .WIDTH(WIDTH)
    ) alu_inst (
        .clk_i   (clk_i),
        .rst_i   (rst_i),
        .valid_i (valid_i),
        .first_i (first_i),
        .second_i(second_i),
        .opcode_i(opcode_i),
        .valid_o (valid_o),
        .result_o(result_o)
    );

    // T = 10 нс
    always #5 clk_i = ~clk_i;

    initial begin
        $dumpvars;

        clk_i    = 0;
        rst_i    = 1;
        valid_i  = 0;
        first_i  = 0;
        second_i = 0;
        opcode_i = 0;

        @(posedge clk_i);
        #1;
        rst_i = 0;

        // Сложение (знаковое)
        valid_i  = 1;
        opcode_i = 2'b00;
        first_i  = 8'd10;
        second_i = 8'd15;
        // expected: result_o <= 0x19, valid_o <= 1.
        @(posedge clk_i); 
        #1;

        // second_i <= first_i
        valid_i  = 1;
        opcode_i = 2'b01;
        first_i  = 8'hAA;
        second_i = 8'hBB;
        // expected: result_o <= 0x00 (false)
        @(posedge clk_i);
        #1;

        // Логический сдвиг second_i влево на first_i
        valid_i  = 1;
        opcode_i = 2'b10;
        first_i  = 8'd3;
        second_i = 8'b0000_1111;
        // expected: 0000_1111 << 3 = 0111_1000 (0x78)
        @(posedge clk_i);
        #1;

        // Побитовое НЕ-ИЛИ
        valid_i  = 1;
        opcode_i = 2'b11;
        first_i  = 8'b1010_1010;
        second_i = 8'b0101_0101;
        // expected: ИЛИ -> 1111_1111, НЕ -> 0000_0000
        @(posedge clk_i);
        #1;

        // если valid_i = 0
        valid_i  = 0;
        opcode_i = 2'b00;   // попытка сложения
        first_i  = 8'd100;
        second_i = 8'd100;
        // expected: result_o не изменится; valid_o <= 0
        @(posedge clk_i);
        #1;
        
        @(posedge clk_i);
        
        $finish;
    end

endmodule

ALU_Register/dump.vcd
$date
	Mon Mar 16 00:24:29 2026
$end
$version
	Icarus Verilog
$end
$timescale
	1ps
$end
$scope module alu_register_tb $end
$var wire 1 ! valid_o $end
$var wire 8 " result_o [7:0] $end
$var reg 1 # clk_i $end
$var reg 8 $ first_i [7:0] $end
$var reg 2 % opcode_i [1:0] $end
$var reg 1 & rst_i $end
$var reg 8 ' second_i [7:0] $end
$var reg 1 ( valid_i $end
$scope module alu_inst $end
$var wire 1 # clk_i $end
$var wire 8 ) first_i [7:0] $end
$var wire 2 * opcode_i [1:0] $end
$var wire 1 & rst_i $end
$var wire 8 + second_i [7:0] $end
$var wire 1 ( valid_i $end
$var reg 8 , alu_result [7:0] $end
$var reg 8 - result_o [7:0] $end
$var reg 1 ! valid_o $end
$upscope $end
$upscope $end
$enddefinitions $end
#0
$dumpvars
bx -
b0 ,
b0 +
b0 *
b0 )
0(
b0 '
1&
b0 %
b0 $
0#
bx "
x!
$end
#5000
0!
1#
#6000
b11001 ,
b1111 '
b1111 +
b1010 $
b1010 )
1(
0&
#10000
0#
#15000
b11001 "
b11001 -
1!
1#
#16000
b0 ,
b10111011 '
b10111011 +
b10101010 $
b10101010 )
b1 %
b1 *
#20000
0#
#25000
b0 "
b0 -
1#
#26000
b1111000 ,
b1111 '
b1111 +
b11 $
b11 )
b10 %
b10 *
#30000
0#
#35000
b1111000 "
b1111000 -
1#
#36000
b0 ,
b1010101 '
b1010101 +
b10101010 $
b10101010 )
b11 %
b11 *
#40000
0#
#45000
b0 "
b0 -
1#
#46000
b11001000 ,
b1100100 '
b1100100 +
b1100100 $
b1100100 )
b0 %
b0 *
0(
#50000
0#
#55000
0!
1#
