Sber_signal_edge_detector/edge_detector.v
module edge_detector (
    input  wire       clk_i,
    input  wire       rst_i,
    input  wire       signal_i,
    output reg  [1:0] detect_o
);

    reg signal_prev;

    always @(posedge clk_i)
    begin
    
        if (rst_i) 
        begin
            signal_prev <= 1'b0;
            detect_o    <= 2'b00;
        end
        
        else begin
            signal_prev <= signal_i;

            if (signal_i == 1'b1 && signal_prev == 1'b0)
            begin
                detect_o <= 2'b01;
            end

            else if (signal_i == 1'b0 && signal_prev == 1'b1)
            begin
                detect_o <= 2'b10;
            end
            
            else begin
                detect_o <= 2'b00;
            end
        end
    end

endmodule

Sber_signal_edge_detector/edge_detector_tb.v
`timescale 1ns / 1ps

module edge_detector_tb();

    reg        clk_i;
    reg        rst_i;
    reg        signal_i;

    wire [1:0] detect_o;

    edge_detector dut (
        .clk_i   (clk_i),
        .rst_i   (rst_i),
        .signal_i(signal_i),
        .detect_o(detect_o)
    );

    // T = 10 нс
    always #5 clk_i = ~clk_i;

    initial begin
        $dumpvars;

        clk_i    = 0;
        rst_i    = 1;
        signal_i = 0;

        @(posedge clk_i);
        #1; // имитирует задержку распространения и предотвращаеь состояние гонки
        rst_i = 0;

        // expected: detect_o <= 2'b00
        @(posedge clk_i); 
        #1;


        // передний фронт
        signal_i = 1;
        // expected: detect_o <= 2'b01 на следующем такте
        @(posedge clk_i);
        #1;

        // expected: detect_o <= 2'b00.
        @(posedge clk_i);
        #1;

        // задний фронт
        signal_i = 0;
        // expected: detect_o <= 2'b10 на следующем такте.
        @(posedge clk_i);
        #1;
        
        // короткий импульс
        #2 signal_i = 1;
        #4 signal_i = 0;
        
        // expected: detect_o <= 2'b00 - импульс проигнорирован
        @(posedge clk_i);
        #1;

        @(posedge clk_i);
        
        $finish;
    end

endmodule

Sber_signal_edge_detector/dump.vcd
$date
	Tue Apr 14 21:47:53 2026
$end
$version
	Icarus Verilog
$end
$timescale
	1ps
$end
$scope module edge_detector_tb $end
$var wire 2 ! detect_o [1:0] $end
$var reg 1 " clk_i $end
$var reg 1 # rst_i $end
$var reg 1 $ signal_i $end
$scope module dut $end
$var wire 1 " clk_i $end
$var wire 1 # rst_i $end
$var wire 1 $ signal_i $end
$var reg 2 % detect_o [1:0] $end
$var reg 1 & signal_prev $end
$upscope $end
$upscope $end
$enddefinitions $end
#0
$dumpvars
x&
bx %
0$
1#
0"
bx !
$end
#5000
b0 !
b0 %
0&
1"
#6000
0#
#10000
0"
#15000
1"
#16000
1$
#20000
0"
#25000
b1 !
b1 %
1&
1"
#30000
0"
#35000
b0 !
b0 %
1"
#36000
0$
#40000
0"
#45000
b10 !
b10 %
0&
1"
#48000
1$
#50000
0"
#52000
0$
#55000
b0 !
b0 %
1"
